[
  {
    "cpt_code": "90791",
    "category": "mh_sud",
    "description": "Psychiatric diagnostic evaluation",
    "source": "CMS CY2025 E/M Code List (hardcoded fallback)"
  },
  {
    "cpt_code": "90792",
    "category": "mh_sud",
    "description": "Psychiatric diagnostic evaluation with medical services",
    "source": "CMS CY2025 E/M Code List (hardcoded fallback)"
  },
  {
    "cpt_code": "90832",
    "category": "mh_sud",
    "description": "Psychotherapy, 30 minutes",
    "source": "CMS CY2025 E/M Code List (hardcoded fallback)"
  },
  {
    "cpt_code": "90833",
    "category": "mh_sud",
    "description": "Psychotherapy, 30 minutes, add-on to E/M",
    "source": "CMS CY2025 E/M Code List (hardcoded fallback)"
  },
  {
    "cpt_code": "90834",
    "category": "mh_sud",
    "description": "Psychotherapy, 45 minutes",
    "source": "CMS CY2025 E/M Code List (hardcoded fallback)"
  },
  {
    "cpt_code": "90836",
    "category": "mh_sud",
    "description": "Psychotherapy, 45 minutes, add-on to E/M",
    "source": "CMS CY2025 E/M Code List (hardcoded fallback)"
  },
  {
    "cpt_code": "90837",
    "category": "mh_sud",
    "description": "Psychotherapy, 60 minutes",
    "source": "CMS CY2025 E/M Code List (hardcoded fallback)"
  },
  {
    "cpt_code": "90838",
    "category": "mh_sud",
    "description": "Psychotherapy, 60 minutes, add-on to E/M",
    "source": "CMS CY2025 E/M Code List (hardcoded fallback)"
  },
  {
    "cpt_code": "90839",
    "category": "mh_sud",
    "description": "Psychotherapy for crisis, first 60 minutes",
    "source": "CMS CY2025 E/M Code List (hardcoded fallback)"
  },
  {
    "cpt_code": "90840",
    "category": "mh_sud",
    "description": "Psychotherapy for crisis, each additional 30 minutes",
    "source": "CMS CY2025 E/M Code List (hardcoded fallback)"
  },
  {
    "cpt_code": "90845",
    "category": "mh_sud",
    "description": "Psychoanalysis",
    "source": "CMS CY2025 E/M Code List (hardcoded fallback)"
  },
  {
    "cpt_code": "90846",
    "category": "mh_sud",
    "description": "Family psychotherapy without patient",
    "source": "CMS CY2025 E/M Code List (hardcoded fallback)"
  },
  {
    "cpt_code": "90847",
    "category": "mh_sud",
    "description": "Family/couples psychotherapy with patient",
    "source": "CMS CY2025 E/M Code List (hardcoded fallback)"
  },
  {
    "cpt_code": "90849",
    "category": "mh_sud",
    "description": "Multiple-family group psychotherapy",
    "source": "CMS CY2025 E/M Code List (hardcoded fallback)"
  },
  {
    "cpt_code": "90853",
    "category": "mh_sud",
    "description": "Group psychotherapy",
    "source": "CMS CY2025 E/M Code List (hardcoded fallback)"
  },
  {
    "cpt_code": "90863",
    "category": "mh_sud",
    "description": "Pharmacologic management with psychotherapy",
    "source": "CMS CY2025 E/M Code List (hardcoded fallback)"
  },
  {
    "cpt_code": "99221",
    "category": "mh_sud",
    "description": "Initial hospital care, straightforward/low MDM",
    "source": "CMS CY2025 E/M Code List (hardcoded fallback)"
  },
  {
    "cpt_code": "99222",
    "category": "mh_sud",
    "description": "Initial hospital care, moderate MDM",
    "source": "CMS CY2025 E/M Code List (hardcoded fallback)"
  },
  {
    "cpt_code": "99223",
    "category": "mh_sud",
    "description": "Initial hospital care, high MDM",
    "source": "CMS CY2025 E/M Code List (hardcoded fallback)"
  },
  {
    "cpt_code": "99231",
    "category": "mh_sud",
    "description": "Subsequent hospital care, straightforward/low MDM",
    "source": "CMS CY2025 E/M Code List (hardcoded fallback)"
  },
  {
    "cpt_code": "99232",
    "category": "mh_sud",
    "description": "Subsequent hospital care, moderate MDM",
    "source": "CMS CY2025 E/M Code List (hardcoded fallback)"
  },
  {
    "cpt_code": "99233",
    "category": "mh_sud",
    "description": "Subsequent hospital care, high MDM",
    "source": "CMS CY2025 E/M Code List (hardcoded fallback)"
  },
  {
    "cpt_code": "99281",
    "category": "mh_sud",
    "description": "Emergency department visit, self-limited",
    "source": "CMS CY2025 E/M Code List (hardcoded fallback)"
  },
  {
    "cpt_code": "99282",
    "category": "mh_sud",
    "description": "Emergency department visit, low severity",
    "source": "CMS CY2025 E/M Code List (hardcoded fallback)"
  },
  {
    "cpt_code": "99283",
    "category": "mh_sud",
    "description": "Emergency department visit, moderate severity",
    "source": "CMS CY2025 E/M Code List (hardcoded fallback)"
  },
  {
    "cpt_code": "99284",
    "category": "mh_sud",
    "description": "Emergency department visit, high severity",
    "source": "CMS CY2025 E/M Code List (hardcoded fallback)"
  },
  {
    "cpt_code": "99285",
    "category": "mh_sud",
    "description": "Emergency department visit, high severity with threat",
    "source": "CMS CY2025 E/M Code List (hardcoded fallback)"
  },
  {
    "cpt_code": "59025",
    "category": "obgyn",
    "description": "Fetal non-stress test",
    "source": "CMS CY2025 E/M Code List (hardcoded fallback)"
  },
  {
    "cpt_code": "59400",
    "category": "obgyn",
    "description": "Routine obstetric care, antepartum, delivery, postpartum",
    "source": "CMS CY2025 E/M Code List (hardcoded fallback)"
  },
  {
    "cpt_code": "59510",
    "category": "obgyn",
    "description": "Cesarean delivery, including antepartum and postpartum care",
    "source": "CMS CY2025 E/M Code List (hardcoded fallback)"
  },
  {
    "cpt_code": "59610",
    "category": "obgyn",
    "description": "VBAC, including antepartum and postpartum care",
    "source": "CMS CY2025 E/M Code List (hardcoded fallback)"
  },
  {
    "cpt_code": "76801",
    "category": "obgyn",
    "description": "Ultrasound, pregnant uterus, first trimester, single fetus",
    "source": "CMS CY2025 E/M Code List (hardcoded fallback)"
  },
  {
    "cpt_code": "76805",
    "category": "obgyn",
    "description": "Ultrasound, pregnant uterus, after first trimester, single fetus",
    "source": "CMS CY2025 E/M Code List (hardcoded fallback)"
  },
  {
    "cpt_code": "76811",
    "category": "obgyn",
    "description": "Ultrasound, pregnant uterus, detailed fetal anatomic exam",
    "source": "CMS CY2025 E/M Code List (hardcoded fallback)"
  },
  {
    "cpt_code": "76812",
    "category": "obgyn",
    "description": "Ultrasound, pregnant uterus, detailed, each additional fetus",
    "source": "CMS CY2025 E/M Code List (hardcoded fallback)"
  },
  {
    "cpt_code": "76813",
    "category": "obgyn",
    "description": "Ultrasound, nuchal translucency, first trimester, single fetus",
    "source": "CMS CY2025 E/M Code List (hardcoded fallback)"
  },
  {
    "cpt_code": "76814",
    "category": "obgyn",
    "description": "Ultrasound, nuchal translucency, each additional fetus",
    "source": "CMS CY2025 E/M Code List (hardcoded fallback)"
  },
  {
    "cpt_code": "76815",
    "category": "obgyn",
    "description": "Ultrasound, pregnant uterus, limited",
    "source": "CMS CY2025 E/M Code List (hardcoded fallback)"
  },
  {
    "cpt_code": "76816",
    "category": "obgyn",
    "description": "Ultrasound, pregnant uterus, follow-up",
    "source": "CMS CY2025 E/M Code List (hardcoded fallback)"
  },
  {
    "cpt_code": "76817",
    "category": "obgyn",
    "description": "Ultrasound, transvaginal",
    "source": "CMS CY2025 E/M Code List (hardcoded fallback)"
  },
  {
    "cpt_code": "76818",
    "category": "obgyn",
    "description": "Fetal biophysical profile with NST",
    "source": "CMS CY2025 E/M Code List (hardcoded fallback)"
  },
  {
    "cpt_code": "76819",
    "category": "obgyn",
    "description": "Fetal biophysical profile without NST",
    "source": "CMS CY2025 E/M Code List (hardcoded fallback)"
  },
  {
    "cpt_code": "76820",
    "category": "obgyn",
    "description": "Doppler velocimetry, fetal umbilical artery",
    "source": "CMS CY2025 E/M Code List (hardcoded fallback)"
  },
  {
    "cpt_code": "76821",
    "category": "obgyn",
    "description": "Doppler velocimetry, fetal middle cerebral artery",
    "source": "CMS CY2025 E/M Code List (hardcoded fallback)"
  },
  {
    "cpt_code": "81025",
    "category": "obgyn",
    "description": "Urine pregnancy test",
    "source": "CMS CY2025 E/M Code List (hardcoded fallback)"
  },
  {
    "cpt_code": "99202",
    "category": "primary_care",
    "description": "Office/outpatient visit, new patient, straightforward MDM",
    "source": "CMS CY2025 E/M Code List (hardcoded fallback)"
  },
  {
    "cpt_code": "99203",
    "category": "primary_care",
    "description": "Office/outpatient visit, new patient, low MDM",
    "source": "CMS CY2025 E/M Code List (hardcoded fallback)"
  },
  {
    "cpt_code": "99204",
    "category": "primary_care",
    "description": "Office/outpatient visit, new patient, moderate MDM",
    "source": "CMS CY2025 E/M Code List (hardcoded fallback)"
  },
  {
    "cpt_code": "99205",
    "category": "primary_care",
    "description": "Office/outpatient visit, new patient, high MDM",
    "source": "CMS CY2025 E/M Code List (hardcoded fallback)"
  },
  {
    "cpt_code": "99211",
    "category": "primary_care",
    "description": "Office/outpatient visit, established patient, may not require physician",
    "source": "CMS CY2025 E/M Code List (hardcoded fallback)"
  },
  {
    "cpt_code": "99212",
    "category": "primary_care",
    "description": "Office/outpatient visit, established patient, straightforward MDM",
    "source": "CMS CY2025 E/M Code List (hardcoded fallback)"
  },
  {
    "cpt_code": "99213",
    "category": "primary_care",
    "description": "Office/outpatient visit, established patient, low MDM",
    "source": "CMS CY2025 E/M Code List (hardcoded fallback)"
  },
  {
    "cpt_code": "99214",
    "category": "primary_care",
    "description": "Office/outpatient visit, established patient, moderate MDM",
    "source": "CMS CY2025 E/M Code List (hardcoded fallback)"
  },
  {
    "cpt_code": "99215",
    "category": "primary_care",
    "description": "Office/outpatient visit, established patient, high MDM",
    "source": "CMS CY2025 E/M Code List (hardcoded fallback)"
  },
  {
    "cpt_code": "99381",
    "category": "primary_care",
    "description": "Initial preventive medicine, infant",
    "source": "CMS CY2025 E/M Code List (hardcoded fallback)"
  },
  {
    "cpt_code": "99382",
    "category": "primary_care",
    "description": "Initial preventive medicine, age 1-4",
    "source": "CMS CY2025 E/M Code List (hardcoded fallback)"
  },
  {
    "cpt_code": "99383",
    "category": "primary_care",
    "description": "Initial preventive medicine, age 5-11",
    "source": "CMS CY2025 E/M Code List (hardcoded fallback)"
  },
  {
    "cpt_code": "99384",
    "category": "primary_care",
    "description": "Initial preventive medicine, age 12-17",
    "source": "CMS CY2025 E/M Code List (hardcoded fallback)"
  },
  {
    "cpt_code": "99385",
    "category": "primary_care",
    "description": "Initial preventive medicine, age 18-39",
    "source": "CMS CY2025 E/M Code List (hardcoded fallback)"
  },
  {
    "cpt_code": "99386",
    "category": "primary_care",
    "description": "Initial preventive medicine, age 40-64",
    "source": "CMS CY2025 E/M Code List (hardcoded fallback)"
  },
  {
    "cpt_code": "99387",
    "category": "primary_care",
    "description": "Initial preventive medicine, age 65+",
    "source": "CMS CY2025 E/M Code List (hardcoded fallback)"
  },
  {
    "cpt_code": "99391",
    "category": "primary_care",
    "description": "Periodic preventive medicine, infant",
    "source": "CMS CY2025 E/M Code List (hardcoded fallback)"
  },
  {
    "cpt_code": "99392",
    "category": "primary_care",
    "description": "Periodic preventive medicine, age 1-4",
    "source": "CMS CY2025 E/M Code List (hardcoded fallback)"
  },
  {
    "cpt_code": "99393",
    "category": "primary_care",
    "description": "Periodic preventive medicine, age 5-11",
    "source": "CMS CY2025 E/M Code List (hardcoded fallback)"
  },
  {
    "cpt_code": "99394",
    "category": "primary_care",
    "description": "Periodic preventive medicine, age 12-17",
    "source": "CMS CY2025 E/M Code List (hardcoded fallback)"
  },
  {
    "cpt_code": "99395",
    "category": "primary_care",
    "description": "Periodic preventive medicine, age 18-39",
    "source": "CMS CY2025 E/M Code List (hardcoded fallback)"
  },
  {
    "cpt_code": "99396",
    "category": "primary_care",
    "description": "Periodic preventive medicine, age 40-64",
    "source": "CMS CY2025 E/M Code List (hardcoded fallback)"
  },
  {
    "cpt_code": "99397",
    "category": "primary_care",
    "description": "Periodic preventive medicine, age 65+",
    "source": "CMS CY2025 E/M Code List (hardcoded fallback)"
  },
  {
    "cpt_code": "99490",
    "category": "primary_care",
    "description": "Chronic care management, 20+ minutes",
    "source": "CMS CY2025 E/M Code List (hardcoded fallback)"
  },
  {
    "cpt_code": "99491",
    "category": "primary_care",
    "description": "Chronic care management, 30+ minutes, physician",
    "source": "CMS CY2025 E/M Code List (hardcoded fallback)"
  },
  {
    "cpt_code": "99495",
    "category": "primary_care",
    "description": "Transitional care management, face-to-face within 7 days",
    "source": "CMS CY2025 E/M Code List (hardcoded fallback)"
  },
  {
    "cpt_code": "99496",
    "category": "primary_care",
    "description": "Transitional care management, face-to-face within 14 days",
    "source": "CMS CY2025 E/M Code List (hardcoded fallback)"
  },
  {
    "cpt_code": "G0438",
    "category": "primary_care",
    "description": "Annual wellness visit, initial",
    "source": "CMS CY2025 E/M Code List (hardcoded fallback)"
  },
  {
    "cpt_code": "G0439",
    "category": "primary_care",
    "description": "Annual wellness visit, subsequent",
    "source": "CMS CY2025 E/M Code List (hardcoded fallback)"
  }
]